somnia_data_streams_sdk/__init__.py
somnia_data_streams_sdk/chains.py
somnia_data_streams_sdk/constants.py
somnia_data_streams_sdk/sdk.py
somnia_data_streams_sdk/modules/__init__.py
somnia_data_streams_sdk/modules/encoder.py
somnia_data_streams_sdk/modules/streams.py
somnia_data_streams_sdk/services/__init__.py
somnia_data_streams_sdk/services/logs.py
somnia_data_streams_sdk/services/web3_client.py
somnia_data_streams_sdk/services/smart_contracts/__init__.py
somnia_data_streams_sdk/services/smart_contracts/constants.py
somnia_data_streams_sdk/services/smart_contracts/contract_manager.py
somnia_data_streams_sdk/services/smart_contracts/abis/__init__.py
somnia_data_streams_sdk/services/smart_contracts/abis/streams_abi.py
somnia_data_streams_sdk/services/smart_contracts/addresses/__init__.py
somnia_data_streams_sdk/services/smart_contracts/addresses/contract_addresses.py
somnia_data_streams_sdk/types/__init__.py
somnia_data_streams_sdk/types/client.py
somnia_data_streams_sdk/types/contracts.py
somnia_data_streams_sdk/types/streams.py
somnia_data_streams_sdk/utils/__init__.py
somnia_data_streams_sdk/utils/validation.py
somnia_data_streams_sdk-0.11.0.dist-info/METADATA
somnia_data_streams_sdk-0.11.0.dist-info/WHEEL
somnia_data_streams_sdk-0.11.0.dist-info/licenses/LICENSE
somnia_data_streams_sdk-0.11.0.dist-info/RECORD
