Metadata-Version: 2.4
Name: somnia-data-streams-sdk
Version: 0.11.0
Summary: A Python SDK for Somnia data streams with first class reactivity support
Project-URL: Homepage, https://github.com/nickyharpor/somnia_data_streams_sdk
Project-URL: Documentation, https://github.com/nickyharpor/somnia_data_streams_sdk
Project-URL: Repository, https://github.com/nickyharpor/somnia_data_streams_sdk
Author: Nicky Harpor
License: MIT License
License-File: LICENSE
Keywords: blockchain,somnia,streams,web3
Classifier: Development Status :: 4 - Beta
Classifier: Intended Audience :: Developers
Classifier: Programming Language :: Python :: 3
Classifier: Programming Language :: Python :: 3.8
Classifier: Programming Language :: Python :: 3.9
Classifier: Programming Language :: Python :: 3.10
Classifier: Programming Language :: Python :: 3.11
Classifier: Programming Language :: Python :: 3.12
Requires-Python: >=3.8
Requires-Dist: eth-abi>=4.0.0
Requires-Dist: eth-utils>=2.0.0
Requires-Dist: typing-extensions>=4.0.0
Requires-Dist: web3>=6.0.0
Requires-Dist: websockets>=11.0
Provides-Extra: dev
Requires-Dist: black>=23.0.0; extra == 'dev'
Requires-Dist: build>=1.3.0; extra == 'dev'
Requires-Dist: mypy>=1.0.0; extra == 'dev'
Requires-Dist: pylint>=2.0.0; extra == 'dev'
Requires-Dist: pytest-asyncio>=0.21.0; extra == 'dev'
Requires-Dist: pytest>=8.3.5; extra == 'dev'
Requires-Dist: twine>=6.2.0; extra == 'dev'
